DataScienceHelpers/__init__.py
DataScienceHelpers/imports.py
DataScienceHelpers/rpy2.py
DataScienceHelpers/structred_fastai.py
DataScienceHelpers-1.0.0.dist-info/METADATA
DataScienceHelpers-1.0.0.dist-info/WHEEL
DataScienceHelpers-1.0.0.dist-info/top_level.txt
DataScienceHelpers-1.0.0.dist-info/RECORD
