Metadata-Version: 2.1
Name: DataScienceHelpers
Version: 1.0.0
Summary: Helper modules for doing data cleaning, training, exploration, etc.
Home-page: UNKNOWN
Author: Max Taggart
Author-email: max.taggart@healthcatalyst.com
License: UNKNOWN
Platform: UNKNOWN
Classifier: Programming Language :: Python :: 3.7
Classifier: License :: OSI Approved :: MIT License
Classifier: Operating System :: OS Independent
Requires-Dist: scikit-learn
Requires-Dist: pandas
Requires-Dist: numpy
Requires-Dist: ipython
Requires-Dist: bcolz
Requires-Dist: graphviz
Requires-Dist: sklearn-pandas
Requires-Dist: isoweek
Requires-Dist: pandas-summary
